Katal-0.3.3.dist-info/DESCRIPTION.rst
Katal-0.3.3.dist-info/METADATA
Katal-0.3.3.dist-info/RECORD
Katal-0.3.3.dist-info/WHEEL
Katal-0.3.3.dist-info/entry_points.txt
Katal-0.3.3.dist-info/metadata.json
Katal-0.3.3.dist-info/top_level.txt
katal/__init__.py
katal/katal.py
