Metadata-Version: 2.0
Name: Katal
Version: 0.3.3
Summary: files' catalogue manager
Home-page: https://github.com/suizokukan/katal
Author: Xavier Faure (suizokukan / 94.23.197.37)
Author-email: suizokukan @T orange D@T fr
License: GPL-3.0
Keywords: file manager tags
Platform: UNKNOWN
Classifier: Development Status :: 5 - Production/Stable
Classifier: Intended Audience :: End Users/Desktop
Classifier: Topic :: Utilities
Classifier: License :: OSI Approved :: GNU General Public License v3 (GPLv3)
Classifier: Programming Language :: Python :: 3
